README.md
arikaim-server
setup.py
arikaim.egg-info/PKG-INFO
arikaim.egg-info/SOURCES.txt
arikaim.egg-info/dependency_links.txt
arikaim.egg-info/requires.txt
arikaim.egg-info/top_level.txt
arikaim/core/action.py
arikaim/core/app.py
arikaim/core/container.py
arikaim/core/controller.py
arikaim/core/driver.py
arikaim/core/errors.py
arikaim/core/file.py
arikaim/core/logger.py
arikaim/core/packages.py
arikaim/core/path.py
arikaim/core/redis.py
arikaim/core/request.py
arikaim/core/response.py
arikaim/core/server.py
arikaim/core/service.py
arikaim/core/services.py
arikaim/core/utils.py
arikaim/core/access/access.py
arikaim/core/access/auth_error.py
arikaim/core/access/middleware.py
arikaim/core/access/quota_error.py
arikaim/core/access/user.py
arikaim/core/access/providers/php_redis_session.py
arikaim/core/access/providers/php_session.py
arikaim/core/access/providers/public.py
arikaim/core/access/providers/token.py
arikaim/core/admin/admin.py
arikaim/core/admin/controllers/service.py
arikaim/core/admin/controllers/service_route.py
arikaim/core/admin/controllers/service_routes.py
arikaim/core/admin/controllers/services_list.py
arikaim/core/collection/descriptor.py
arikaim/core/collection/properties.py
arikaim/core/collection/property.py
arikaim/core/console/app.py
arikaim/core/console/config.py
arikaim/core/console/install.py
arikaim/core/console/packages.py
arikaim/core/console/queue.py
arikaim/core/console/services.py
arikaim/core/console/templates/config_file.py
arikaim/core/db/db.py
arikaim/core/db/models/access_tokens.py
arikaim/core/db/models/drivers.py
arikaim/core/db/models/options.py
arikaim/core/db/models/permission_relations.py
arikaim/core/db/models/permissions.py
arikaim/core/db/models/users.py
arikaim/core/middleware/exception_handler.py
arikaim/core/middleware/sanitize.py
arikaim/core/middleware/system.py
arikaim/core/queue/job.py
arikaim/core/queue/queue.py
arikaim/core/traits/controller/run_action.py
arikaim/core/view/main.py