Metadata-Version: 2.1
Name: arikaim
Version: 0.5.32
Summary: Arikaim services server
Home-page: https://github.com/arikaim/arikaim-services-server.git
Download-URL: 
Author: Intersoft Ltd
Author-email: info@arikaim.com
License: MIT License
Keywords: arikaim
Requires-Dist: uvicorn
Requires-Dist: starlette==0.41.3
Requires-Dist: python-multipart
Requires-Dist: pymysql
Requires-Dist: sqlmodel
Requires-Dist: click
Requires-Dist: bleach
Requires-Dist: rich
Requires-Dist: textual
Requires-Dist: psutil
Requires-Dist: requests
Requires-Dist: pydantic
Requires-Dist: schema
Requires-Dist: redis
Requires-Dist: Jinja2
